timed_audio_player/__init__.py
timed_audio_player/main.py
timed_audio_player-1.0.2.dist-info/LICENSE
timed_audio_player-1.0.2.dist-info/METADATA
timed_audio_player-1.0.2.dist-info/WHEEL
timed_audio_player-1.0.2.dist-info/entry_points.txt
timed_audio_player-1.0.2.dist-info/top_level.txt
timed_audio_player-1.0.2.dist-info/RECORD
