Metadata-Version: 2.1
Name: timed-audio-player
Version: 1.0.2
Summary: An audio player that will play audio files in a directory for a specified amount of time.
License: GNU GENERAL PUBLIC LICENSE
Project-URL: Homepage, https://github.com/ambauma/TimedAudioPlayer
Project-URL: Documentation, https://github.com/ambauma/TimedAudioPlayer
Project-URL: Repository, https://github.com/ambauma/TimedAudioPlayer
Project-URL: Issues, https://github.com/ambauma/TimedAudioPlayer/issues
Project-URL: Changelog, https://github.com/ambauma/TimedAudioPlayer/blob/master/CHANGELOG.md
Requires-Python: >=3.9
License-File: LICENSE
Requires-Dist: python-vlc<4,>=3.0.21203
Provides-Extra: test
Requires-Dist: pytest-cov; extra == "test"
Requires-Dist: black; extra == "test"
Requires-Dist: pydocstyle; extra == "test"
Requires-Dist: pylint; extra == "test"
Requires-Dist: mockito; extra == "test"
